LICENSE
MANIFEST.in
README.md
requirements.txt
setup.py
certchecker/__init__.py
certchecker/__main__.py
certchecker/certchecker.py
certchecker.egg-info/PKG-INFO
certchecker.egg-info/SOURCES.txt
certchecker.egg-info/dependency_links.txt
certchecker.egg-info/entry_points.txt
certchecker.egg-info/requires.txt
certchecker.egg-info/top_level.txt