Metadata-Version: 1.0
Name: certchecker
Version: 0.2.4
Summary: A tool to check SSL Certificates in AWS
Home-page: https://github.com/tsiang/certchecker
Author: Steven Tsiang
Author-email: steven@scopely.com
License: Apache License
